[
    {
        "product_id": "P0001",
        "seller_id": "S011",
        "title": "W Purple Cotton Kurta",
        "brand": "W",
        "category": "Kurta",
        "price": 1599,
        "color": "Purple",
        "material": "Cotton",
        "occasion": "Office",
        "gender": "Women",
        "season": "Spring",
        "inventory": 47,
        "rating": 4.3,
        "discount": 0,
        "available_regions": [
            "Coimbatore",
            "Jaipur",
            "Lucknow"
        ]
    },
    {
        "product_id": "P0002",
        "seller_id": "S005",
        "title": "W Yellow Cotton Kurta",
        "brand": "W",
        "category": "Kurta",
        "price": 1699,
        "color": "Yellow",
        "material": "Cotton",
        "occasion": "Casual",
        "gender": "Women",
        "season": "Summer",
        "inventory": 125,
        "rating": 4.4,
        "discount": 20,
        "available_regions": [
            "Indore",
            "Jaipur",
            "Lucknow",
            "Nagpur",
            "Patna"
        ]
    },
    {
        "product_id": "P0003",
        "seller_id": "S012",
        "title": "Libas Purple Silk Kurta",
        "brand": "Libas",
        "category": "Kurta",
        "price": 1199,
        "color": "Purple",
        "material": "Silk",
        "occasion": "Festive",
        "gender": "Women",
        "season": "Spring",
        "inventory": 120,
        "rating": 4.7,
        "discount": 10,
        "available_regions": [
            "Coimbatore",
            "Indore",
            "Lucknow",
            "Nagpur",
            "Patna"
        ]
    },
    {
        "product_id": "P0004",
        "seller_id": "S004",
        "title": "Anouk Purple Cotton Kurta",
        "brand": "Anouk",
        "category": "Kurta",
        "price": 1899,
        "color": "Purple",
        "material": "Cotton",
        "occasion": "Office",
        "gender": "Women",
        "season": "Summer",
        "inventory": 59,
        "rating": 4.6,
        "discount": 25,
        "available_regions": [
            "Coimbatore",
            "Indore",
            "Jaipur",
            "Nagpur"
        ]
    },
    {
        "product_id": "P0005",
        "seller_id": "S012",
        "title": "Libas Navy Rayon Kurta",
        "brand": "Libas",
        "category": "Kurta",
        "price": 899,
        "color": "Navy",
        "material": "Rayon",
        "occasion": "Casual",
        "gender": "Women",
        "season": "Summer",
        "inventory": 60,
        "rating": 4.4,
        "discount": 30,
        "available_regions": [
            "Coimbatore",
            "Indore",
            "Lucknow",
            "Patna"
        ]
    },
    {
        "product_id": "P0006",
        "seller_id": "S010",
        "title": "Anouk Dark Blue Cotton Kurta",
        "brand": "Anouk",
        "category": "Kurta",
        "price": 1899,
        "color": "Dark Blue",
        "material": "Cotton",
        "occasion": "Casual",
        "gender": "Women",
        "season": "All Season",
        "inventory": 65,
        "rating": 4.7,
        "discount": 15,
        "available_regions": [
            "Coimbatore",
            "Indore",
            "Jaipur",
            "Lucknow",
            "Nagpur",
            "Patna"
        ]
    },
    {
        "product_id": "P0007",
        "seller_id": "S002",
        "title": "Sangria Pink Rayon Kurta",
        "brand": "Sangria",
        "category": "Kurta",
        "price": 1599,
        "color": "Pink",
        "material": "Rayon",
        "occasion": "Office",
        "gender": "Women",
        "season": "Summer",
        "inventory": 89,
        "rating": 4.3,
        "discount": 10,
        "available_regions": [
            "Coimbatore",
            "Indore",
            "Jaipur",
            "Lucknow",
            "Nagpur",
            "Patna"
        ]
    },
    {
        "product_id": "P0008",
        "seller_id": "S009",
        "title": "Sangria Grey Cotton Kurta",
        "brand": "Sangria",
        "category": "Kurta",
        "price": 1599,
        "color": "Grey",
        "material": "Cotton",
        "occasion": "Office",
        "gender": "Women",
        "season": "Spring",
        "inventory": 82,
        "rating": 4.2,
        "discount": 15,
        "available_regions": [
            "Coimbatore",
            "Indore",
            "Lucknow",
            "Patna"
        ]
    },
    {
        "product_id": "P0009",
        "seller_id": "S009",
        "title": "Anouk White Cotton Kurta",
        "brand": "Anouk",
        "category": "Kurta",
        "price": 1399,
        "color": "White",
        "material": "Cotton",
        "occasion": "Office",
        "gender": "Women",
        "season": "Spring",
        "inventory": 104,
        "rating": 4.7,
        "discount": 20,
        "available_regions": [
            "Indore",
            "Nagpur",
            "Patna"
        ]
    },
    {
        "product_id": "P0010",
        "seller_id": "S002",
        "title": "Libas Grey Silk Kurta",
        "brand": "Libas",
        "category": "Kurta",
        "price": 2299,
        "color": "Grey",
        "material": "Silk",
        "occasion": "Festive",
        "gender": "Women",
        "season": "Summer",
        "inventory": 67,
        "rating": 4.4,
        "discount": 20,
        "available_regions": [
            "Indore",
            "Lucknow",
            "Nagpur",
            "Patna"
        ]
    },
    {
        "product_id": "P0011",
        "seller_id": "S011",
        "title": "Sangria Dark Blue Rayon Kurta",
        "brand": "Sangria",
        "category": "Kurta",
        "price": 1399,
        "color": "Dark Blue",
        "material": "Rayon",
        "occasion": "Casual",
        "gender": "Women",
        "season": "Summer",
        "inventory": 52,
        "rating": 4.5,
        "discount": 10,
        "available_regions": [
            "Coimbatore",
            "Indore",
            "Lucknow",
            "Nagpur"
        ]
    },
    {
        "product_id": "P0012",
        "seller_id": "S002",
        "title": "W Green Cotton Kurta",
        "brand": "W",
        "category": "Kurta",
        "price": 1999,
        "color": "Green",
        "material": "Cotton",
        "occasion": "Office",
        "gender": "Women",
        "season": "Summer",
        "inventory": 86,
        "rating": 4.3,
        "discount": 10,
        "available_regions": [
            "Coimbatore",
            "Indore",
            "Jaipur",
            "Lucknow",
            "Nagpur",
            "Patna"
        ]
    },
    {
        "product_id": "P0013",
        "seller_id": "S002",
        "title": "Biba White Rayon Kurta",
        "brand": "Biba",
        "category": "Kurta",
        "price": 699,
        "color": "White",
        "material": "Rayon",
        "occasion": "Casual",
        "gender": "Women",
        "season": "All Season",
        "inventory": 73,
        "rating": 4.0,
        "discount": 10,
        "available_regions": [
            "Jaipur",
            "Lucknow",
            "Nagpur",
            "Patna"
        ]
    },
    {
        "product_id": "P0014",
        "seller_id": "S014",
        "title": "Biba Blue Rayon Kurta",
        "brand": "Biba",
        "category": "Kurta",
        "price": 1899,
        "color": "Blue",
        "material": "Rayon",
        "occasion": "Office",
        "gender": "Women",
        "season": "Summer",
        "inventory": 109,
        "rating": 4.6,
        "discount": 20,
        "available_regions": [
            "Jaipur",
            "Lucknow",
            "Nagpur"
        ]
    },
    {
        "product_id": "P0015",
        "seller_id": "S012",
        "title": "Libas Pink Rayon Kurta",
        "brand": "Libas",
        "category": "Kurta",
        "price": 2199,
        "color": "Pink",
        "material": "Rayon",
        "occasion": "Festive",
        "gender": "Women",
        "season": "Summer",
        "inventory": 111,
        "rating": 4.4,
        "discount": 20,
        "available_regions": [
            "Coimbatore",
            "Indore",
            "Jaipur",
            "Lucknow"
        ]
    },
    {
        "product_id": "P0016",
        "seller_id": "S009",
        "title": "W White Cotton Kurta",
        "brand": "W",
        "category": "Kurta",
        "price": 1999,
        "color": "White",
        "material": "Cotton",
        "occasion": "Casual",
        "gender": "Women",
        "season": "Summer",
        "inventory": 71,
        "rating": 4.4,
        "discount": 20,
        "available_regions": [
            "Coimbatore",
            "Indore",
            "Lucknow",
            "Nagpur"
        ]
    },
    {
        "product_id": "P0017",
        "seller_id": "S001",
        "title": "Sangria Pink Silk Kurta",
        "brand": "Sangria",
        "category": "Kurta",
        "price": 1399,
        "color": "Pink",
        "material": "Silk",
        "occasion": "Festive",
        "gender": "Women",
        "season": "Summer",
        "inventory": 51,
        "rating": 4.5,
        "discount": 20,
        "available_regions": [
            "Coimbatore",
            "Indore",
            "Jaipur",
            "Nagpur",
            "Patna"
        ]
    },
    {
        "product_id": "P0018",
        "seller_id": "S001",
        "title": "Libas Green Linen Kurta",
        "brand": "Libas",
        "category": "Kurta",
        "price": 1199,
        "color": "Green",
        "material": "Linen",
        "occasion": "Casual",
        "gender": "Women",
        "season": "All Season",
        "inventory": 163,
        "rating": 4.4,
        "discount": 10,
        "available_regions": [
            "Indore",
            "Jaipur",
            "Nagpur",
            "Patna"
        ]
    },
    {
        "product_id": "P0019",
        "seller_id": "S014",
        "title": "Anouk Green Silk Kurta",
        "brand": "Anouk",
        "category": "Kurta",
        "price": 1299,
        "color": "Green",
        "material": "Silk",
        "occasion": "Festive",
        "gender": "Women",
        "season": "Summer",
        "inventory": 90,
        "rating": 4.4,
        "discount": 25,
        "available_regions": [
            "Coimbatore",
            "Indore",
            "Jaipur",
            "Lucknow",
            "Patna"
        ]
    },
    {
        "product_id": "P0020",
        "seller_id": "S005",
        "title": "Biba Navy Silk Kurta",
        "brand": "Biba",
        "category": "Kurta",
        "price": 699,
        "color": "Navy",
        "material": "Silk",
        "occasion": "Festive",
        "gender": "Women",
        "season": "Summer",
        "inventory": 73,
        "rating": 4.5,
        "discount": 30,
        "available_regions": [
            "Coimbatore",
            "Indore",
            "Nagpur",
            "Patna"
        ]
    },
    {
        "product_id": "P0021",
        "seller_id": "S014",
        "title": "Libas Purple Rayon Kurta",
        "brand": "Libas",
        "category": "Kurta",
        "price": 1099,
        "color": "Purple",
        "material": "Rayon",
        "occasion": "Festive",
        "gender": "Women",
        "season": "Summer",
        "inventory": 54,
        "rating": 4.3,
        "discount": 0,
        "available_regions": [
            "Coimbatore",
            "Indore",
            "Jaipur",
            "Lucknow",
            "Nagpur"
        ]
    },
    {
        "product_id": "P0022",
        "seller_id": "S012",
        "title": "W Pink Linen Kurta",
        "brand": "W",
        "category": "Kurta",
        "price": 799,
        "color": "Pink",
        "material": "Linen",
        "occasion": "Casual",
        "gender": "Women",
        "season": "All Season",
        "inventory": 125,
        "rating": 4.2,
        "discount": 30,
        "available_regions": [
            "Indore",
            "Jaipur",
            "Lucknow",
            "Patna"
        ]
    },
    {
        "product_id": "P0023",
        "seller_id": "S008",
        "title": "Libas Blue Cotton Kurta",
        "brand": "Libas",
        "category": "Kurta",
        "price": 899,
        "color": "Blue",
        "material": "Cotton",
        "occasion": "Casual",
        "gender": "Women",
        "season": "Summer",
        "inventory": 91,
        "rating": 4.2,
        "discount": 15,
        "available_regions": [
            "Coimbatore",
            "Jaipur",
            "Lucknow",
            "Patna"
        ]
    },
    {
        "product_id": "P0024",
        "seller_id": "S005",
        "title": "Biba Light Blue Linen Kurta",
        "brand": "Biba",
        "category": "Kurta",
        "price": 799,
        "color": "Light Blue",
        "material": "Linen",
        "occasion": "Casual",
        "gender": "Women",
        "season": "Summer",
        "inventory": 99,
        "rating": 4.4,
        "discount": 10,
        "available_regions": [
            "Coimbatore",
            "Indore",
            "Jaipur",
            "Lucknow",
            "Nagpur",
            "Patna"
        ]
    },
    {
        "product_id": "P0025",
        "seller_id": "S013",
        "title": "Sangria Blue Cotton Kurta",
        "brand": "Sangria",
        "category": "Kurta",
        "price": 1299,
        "color": "Blue",
        "material": "Cotton",
        "occasion": "Office",
        "gender": "Women",
        "season": "Summer",
        "inventory": 72,
        "rating": 4.1,
        "discount": 20,
        "available_regions": [
            "Coimbatore",
            "Indore",
            "Jaipur",
            "Lucknow",
            "Patna"
        ]
    },
    {
        "product_id": "P0026",
        "seller_id": "S006",
        "title": "W Blue Silk Kurta",
        "brand": "W",
        "category": "Kurta",
        "price": 1099,
        "color": "Blue",
        "material": "Silk",
        "occasion": "Festive",
        "gender": "Women",
        "season": "Spring",
        "inventory": 76,
        "rating": 4.5,
        "discount": 15,
        "available_regions": [
            "Coimbatore",
            "Indore",
            "Jaipur",
            "Lucknow",
            "Nagpur",
            "Patna"
        ]
    },
    {
        "product_id": "P0027",
        "seller_id": "S003",
        "title": "Biba Blue Linen Kurta",
        "brand": "Biba",
        "category": "Kurta",
        "price": 1499,
        "color": "Blue",
        "material": "Linen",
        "occasion": "Casual",
        "gender": "Women",
        "season": "Spring",
        "inventory": 72,
        "rating": 4.7,
        "discount": 20,
        "available_regions": [
            "Coimbatore",
            "Indore",
            "Jaipur"
        ]
    },
    {
        "product_id": "P0028",
        "seller_id": "S013",
        "title": "Anouk Blue Rayon Kurta",
        "brand": "Anouk",
        "category": "Kurta",
        "price": 699,
        "color": "Blue",
        "material": "Rayon",
        "occasion": "Office",
        "gender": "Women",
        "season": "Spring",
        "inventory": 49,
        "rating": 4.5,
        "discount": 10,
        "available_regions": [
            "Coimbatore",
            "Indore",
            "Jaipur",
            "Lucknow",
            "Nagpur",
            "Patna"
        ]
    },
    {
        "product_id": "P0029",
        "seller_id": "S009",
        "title": "Anouk Blue Silk Kurta",
        "brand": "Anouk",
        "category": "Kurta",
        "price": 899,
        "color": "Blue",
        "material": "Silk",
        "occasion": "Festive",
        "gender": "Women",
        "season": "Summer",
        "inventory": 95,
        "rating": 4.2,
        "discount": 25,
        "available_regions": [
            "Coimbatore",
            "Indore",
            "Jaipur",
            "Nagpur",
            "Patna"
        ]
    },
    {
        "product_id": "P0030",
        "seller_id": "S011",
        "title": "Sangria Dark Blue Cotton Kurta",
        "brand": "Sangria",
        "category": "Kurta",
        "price": 899,
        "color": "Dark Blue",
        "material": "Cotton",
        "occasion": "Casual",
        "gender": "Women",
        "season": "Summer",
        "inventory": 84,
        "rating": 4.2,
        "discount": 10,
        "available_regions": [
            "Coimbatore",
            "Indore",
            "Jaipur",
            "Lucknow",
            "Nagpur",
            "Patna"
        ]
    },
    {
        "product_id": "P0031",
        "seller_id": "S004",
        "title": "Sangria Purple Cotton Kurta",
        "brand": "Sangria",
        "category": "Kurta",
        "price": 699,
        "color": "Purple",
        "material": "Cotton",
        "occasion": "Office",
        "gender": "Women",
        "season": "Summer",
        "inventory": 53,
        "rating": 4.5,
        "discount": 15,
        "available_regions": [
            "Coimbatore",
            "Indore",
            "Lucknow",
            "Patna"
        ]
    },
    {
        "product_id": "P0032",
        "seller_id": "S014",
        "title": "Biba Purple Rayon Kurta",
        "brand": "Biba",
        "category": "Kurta",
        "price": 1099,
        "color": "Purple",
        "material": "Rayon",
        "occasion": "Office",
        "gender": "Women",
        "season": "All Season",
        "inventory": 79,
        "rating": 4.1,
        "discount": 20,
        "available_regions": [
            "Indore",
            "Jaipur",
            "Nagpur",
            "Patna"
        ]
    },
    {
        "product_id": "P0033",
        "seller_id": "S014",
        "title": "Biba Pink Rayon Kurta",
        "brand": "Biba",
        "category": "Kurta",
        "price": 1199,
        "color": "Pink",
        "material": "Rayon",
        "occasion": "Casual",
        "gender": "Women",
        "season": "Spring",
        "inventory": 104,
        "rating": 4.6,
        "discount": 0,
        "available_regions": [
            "Coimbatore",
            "Indore",
            "Jaipur",
            "Lucknow",
            "Nagpur",
            "Patna"
        ]
    },
    {
        "product_id": "P0034",
        "seller_id": "S014",
        "title": "Libas Grey Rayon Kurta",
        "brand": "Libas",
        "category": "Kurta",
        "price": 699,
        "color": "Grey",
        "material": "Rayon",
        "occasion": "Office",
        "gender": "Women",
        "season": "Summer",
        "inventory": 110,
        "rating": 4.4,
        "discount": 40,
        "available_regions": [
            "Indore",
            "Jaipur",
            "Lucknow",
            "Nagpur",
            "Patna"
        ]
    },
    {
        "product_id": "P0035",
        "seller_id": "S010",
        "title": "Libas Purple Cotton Kurta",
        "brand": "Libas",
        "category": "Kurta",
        "price": 2199,
        "color": "Purple",
        "material": "Cotton",
        "occasion": "Office",
        "gender": "Women",
        "season": "Spring",
        "inventory": 61,
        "rating": 4.4,
        "discount": 15,
        "available_regions": [
            "Indore",
            "Jaipur",
            "Lucknow"
        ]
    },
    {
        "product_id": "P0036",
        "seller_id": "S012",
        "title": "W Navy Linen Kurta",
        "brand": "W",
        "category": "Kurta",
        "price": 899,
        "color": "Navy",
        "material": "Linen",
        "occasion": "Casual",
        "gender": "Women",
        "season": "Summer",
        "inventory": 40,
        "rating": 4.2,
        "discount": 10,
        "available_regions": [
            "Coimbatore",
            "Indore",
            "Lucknow",
            "Nagpur",
            "Patna"
        ]
    },
    {
        "product_id": "P0037",
        "seller_id": "S014",
        "title": "Libas Pink Cotton Kurta",
        "brand": "Libas",
        "category": "Kurta",
        "price": 1099,
        "color": "Pink",
        "material": "Cotton",
        "occasion": "Office",
        "gender": "Women",
        "season": "Summer",
        "inventory": 53,
        "rating": 4.4,
        "discount": 15,
        "available_regions": [
            "Coimbatore",
            "Indore",
            "Jaipur",
            "Lucknow",
            "Nagpur",
            "Patna"
        ]
    },
    {
        "product_id": "P0038",
        "seller_id": "S015",
        "title": "Biba Grey Cotton Kurta",
        "brand": "Biba",
        "category": "Kurta",
        "price": 699,
        "color": "Grey",
        "material": "Cotton",
        "occasion": "Casual",
        "gender": "Women",
        "season": "Summer",
        "inventory": 93,
        "rating": 4.3,
        "discount": 15,
        "available_regions": [
            "Coimbatore",
            "Indore",
            "Jaipur",
            "Lucknow",
            "Nagpur",
            "Patna"
        ]
    },
    {
        "product_id": "P0039",
        "seller_id": "S005",
        "title": "Libas Dark Blue Rayon Kurta",
        "brand": "Libas",
        "category": "Kurta",
        "price": 1299,
        "color": "Dark Blue",
        "material": "Rayon",
        "occasion": "Office",
        "gender": "Women",
        "season": "Spring",
        "inventory": 63,
        "rating": 4.4,
        "discount": 10,
        "available_regions": [
            "Coimbatore",
            "Indore",
            "Jaipur",
            "Lucknow",
            "Nagpur",
            "Patna"
        ]
    },
    {
        "product_id": "P0040",
        "seller_id": "S011",
        "title": "Biba Purple Cotton Kurta",
        "brand": "Biba",
        "category": "Kurta",
        "price": 1299,
        "color": "Purple",
        "material": "Cotton",
        "occasion": "Office",
        "gender": "Women",
        "season": "Summer",
        "inventory": 49,
        "rating": 4.4,
        "discount": 15,
        "available_regions": [
            "Coimbatore",
            "Indore",
            "Jaipur",
            "Nagpur",
            "Patna"
        ]
    },
    {
        "product_id": "P0041",
        "seller_id": "S012",
        "title": "Anouk Pink Silk Saree",
        "brand": "Anouk",
        "category": "Saree",
        "price": 1399,
        "color": "Pink",
        "material": "Silk",
        "occasion": "Wedding",
        "gender": "Women",
        "season": "Festive",
        "inventory": 86,
        "rating": 4.6,
        "discount": 20,
        "available_regions": [
            "Coimbatore",
            "Indore",
            "Jaipur",
            "Lucknow",
            "Nagpur"
        ]
    },
    {
        "product_id": "P0042",
        "seller_id": "S009",
        "title": "Anouk Red Georgette Saree",
        "brand": "Anouk",
        "category": "Saree",
        "price": 1599,
        "color": "Red",
        "material": "Georgette",
        "occasion": "Party",
        "gender": "Women",
        "season": "Festive",
        "inventory": 113,
        "rating": 4.3,
        "discount": 25,
        "available_regions": [
            "Indore",
            "Lucknow",
            "Nagpur"
        ]
    },
    {
        "product_id": "P0043",
        "seller_id": "S008",
        "title": "Mitera Blue Silk Saree",
        "brand": "Mitera",
        "category": "Saree",
        "price": 1199,
        "color": "Blue",
        "material": "Silk",
        "occasion": "Wedding",
        "gender": "Women",
        "season": "Festive",
        "inventory": 106,
        "rating": 4.5,
        "discount": 20,
        "available_regions": [
            "Coimbatore",
            "Indore",
            "Jaipur"
        ]
    },
    {
        "product_id": "P0044",
        "seller_id": "S010",
        "title": "Kalini Pink Georgette Saree",
        "brand": "Kalini",
        "category": "Saree",
        "price": 4699,
        "color": "Pink",
        "material": "Georgette",
        "occasion": "Wedding",
        "gender": "Women",
        "season": "All Season",
        "inventory": 68,
        "rating": 4.7,
        "discount": 20,
        "available_regions": [
            "Coimbatore",
            "Indore",
            "Jaipur"
        ]
    },
    {
        "product_id": "P0045",
        "seller_id": "S008",
        "title": "Kalini Red Silk Saree",
        "brand": "Kalini",
        "category": "Saree",
        "price": 2799,
        "color": "Red",
        "material": "Silk",
        "occasion": "Wedding",
        "gender": "Women",
        "season": "All Season",
        "inventory": 73,
        "rating": 4.4,
        "discount": 15,
        "available_regions": [
            "Coimbatore",
            "Indore",
            "Lucknow",
            "Nagpur",
            "Patna"
        ]
    },
    {
        "product_id": "P0046",
        "seller_id": "S007",
        "title": "Sangria Pink Chiffon Saree",
        "brand": "Sangria",
        "category": "Saree",
        "price": 1199,
        "color": "Pink",
        "material": "Chiffon",
        "occasion": "Party",
        "gender": "Women",
        "season": "Festive",
        "inventory": 82,
        "rating": 4.5,
        "discount": 15,
        "available_regions": [
            "Coimbatore",
            "Jaipur",
            "Lucknow",
            "Patna"
        ]
    },
    {
        "product_id": "P0047",
        "seller_id": "S005",
        "title": "Kalini Black Silk Saree",
        "brand": "Kalini",
        "category": "Saree",
        "price": 2799,
        "color": "Black",
        "material": "Silk",
        "occasion": "Festive",
        "gender": "Women",
        "season": "All Season",
        "inventory": 107,
        "rating": 4.3,
        "discount": 15,
        "available_regions": [
            "Lucknow",
            "Nagpur",
            "Patna"
        ]
    },
    {
        "product_id": "P0048",
        "seller_id": "S014",
        "title": "Kalini Green Silk Saree",
        "brand": "Kalini",
        "category": "Saree",
        "price": 2399,
        "color": "Green",
        "material": "Silk",
        "occasion": "Wedding",
        "gender": "Women",
        "season": "All Season",
        "inventory": 173,
        "rating": 4.2,
        "discount": 20,
        "available_regions": [
            "Indore",
            "Jaipur",
            "Lucknow",
            "Nagpur",
            "Patna"
        ]
    },
    {
        "product_id": "P0049",
        "seller_id": "S002",
        "title": "Sangria Red Chiffon Saree",
        "brand": "Sangria",
        "category": "Saree",
        "price": 2099,
        "color": "Red",
        "material": "Chiffon",
        "occasion": "Party",
        "gender": "Women",
        "season": "All Season",
        "inventory": 61,
        "rating": 4.5,
        "discount": 10,
        "available_regions": [
            "Indore",
            "Jaipur",
            "Nagpur",
            "Patna"
        ]
    },
    {
        "product_id": "P0050",
        "seller_id": "S005",
        "title": "Kalini Blue Silk Saree",
        "brand": "Kalini",
        "category": "Saree",
        "price": 1699,
        "color": "Blue",
        "material": "Silk",
        "occasion": "Festive",
        "gender": "Women",
        "season": "All Season",
        "inventory": 104,
        "rating": 4.4,
        "discount": 20,
        "available_regions": [
            "Coimbatore",
            "Nagpur",
            "Patna"
        ]
    },
    {
        "product_id": "P0051",
        "seller_id": "S013",
        "title": "Mitera Red Silk Saree",
        "brand": "Mitera",
        "category": "Saree",
        "price": 1099,
        "color": "Red",
        "material": "Silk",
        "occasion": "Wedding",
        "gender": "Women",
        "season": "All Season",
        "inventory": 78,
        "rating": 4.5,
        "discount": 15,
        "available_regions": [
            "Coimbatore",
            "Indore",
            "Jaipur",
            "Lucknow",
            "Nagpur",
            "Patna"
        ]
    },
    {
        "product_id": "P0052",
        "seller_id": "S008",
        "title": "Kalini Green Georgette Saree",
        "brand": "Kalini",
        "category": "Saree",
        "price": 4099,
        "color": "Green",
        "material": "Georgette",
        "occasion": "Wedding",
        "gender": "Women",
        "season": "Festive",
        "inventory": 71,
        "rating": 4.3,
        "discount": 30,
        "available_regions": [
            "Coimbatore",
            "Indore",
            "Jaipur",
            "Nagpur",
            "Patna"
        ]
    },
    {
        "product_id": "P0053",
        "seller_id": "S015",
        "title": "Anouk Green Georgette Saree",
        "brand": "Anouk",
        "category": "Saree",
        "price": 1199,
        "color": "Green",
        "material": "Georgette",
        "occasion": "Wedding",
        "gender": "Women",
        "season": "All Season",
        "inventory": 118,
        "rating": 4.5,
        "discount": 25,
        "available_regions": [
            "Coimbatore",
            "Indore",
            "Jaipur",
            "Lucknow",
            "Nagpur"
        ]
    },
    {
        "product_id": "P0054",
        "seller_id": "S008",
        "title": "Sangria Green Silk Saree",
        "brand": "Sangria",
        "category": "Saree",
        "price": 1699,
        "color": "Green",
        "material": "Silk",
        "occasion": "Party",
        "gender": "Women",
        "season": "All Season",
        "inventory": 50,
        "rating": 4.3,
        "discount": 15,
        "available_regions": [
            "Coimbatore",
            "Jaipur",
            "Lucknow",
            "Nagpur",
            "Patna"
        ]
    },
    {
        "product_id": "P0055",
        "seller_id": "S011",
        "title": "Anouk Pink Cotton Saree",
        "brand": "Anouk",
        "category": "Saree",
        "price": 3199,
        "color": "Pink",
        "material": "Cotton",
        "occasion": "Festive",
        "gender": "Women",
        "season": "All Season",
        "inventory": 71,
        "rating": 4.3,
        "discount": 30,
        "available_regions": [
            "Coimbatore",
            "Indore",
            "Lucknow",
            "Nagpur"
        ]
    },
    {
        "product_id": "P0056",
        "seller_id": "S007",
        "title": "Sangria Blue Chiffon Saree",
        "brand": "Sangria",
        "category": "Saree",
        "price": 3599,
        "color": "Blue",
        "material": "Chiffon",
        "occasion": "Party",
        "gender": "Women",
        "season": "All Season",
        "inventory": 89,
        "rating": 4.4,
        "discount": 25,
        "available_regions": [
            "Coimbatore",
            "Indore",
            "Lucknow",
            "Nagpur",
            "Patna"
        ]
    },
    {
        "product_id": "P0057",
        "seller_id": "S012",
        "title": "Sangria Black Silk Saree",
        "brand": "Sangria",
        "category": "Saree",
        "price": 3699,
        "color": "Black",
        "material": "Silk",
        "occasion": "Festive",
        "gender": "Women",
        "season": "All Season",
        "inventory": 48,
        "rating": 4.4,
        "discount": 20,
        "available_regions": [
            "Coimbatore",
            "Indore",
            "Jaipur",
            "Nagpur"
        ]
    },
    {
        "product_id": "P0058",
        "seller_id": "S003",
        "title": "Anouk Maroon Cotton Saree",
        "brand": "Anouk",
        "category": "Saree",
        "price": 2799,
        "color": "Maroon",
        "material": "Cotton",
        "occasion": "Festive",
        "gender": "Women",
        "season": "All Season",
        "inventory": 86,
        "rating": 4.4,
        "discount": 25,
        "available_regions": [
            "Coimbatore",
            "Indore",
            "Lucknow",
            "Nagpur",
            "Patna"
        ]
    },
    {
        "product_id": "P0059",
        "seller_id": "S014",
        "title": "Mitera Green Silk Saree",
        "brand": "Mitera",
        "category": "Saree",
        "price": 1799,
        "color": "Green",
        "material": "Silk",
        "occasion": "Festive",
        "gender": "Women",
        "season": "All Season",
        "inventory": 68,
        "rating": 4.2,
        "discount": 20,
        "available_regions": [
            "Coimbatore",
            "Indore",
            "Jaipur",
            "Patna"
        ]
    },
    {
        "product_id": "P0060",
        "seller_id": "S002",
        "title": "Kalini Black Georgette Saree",
        "brand": "Kalini",
        "category": "Saree",
        "price": 1999,
        "color": "Black",
        "material": "Georgette",
        "occasion": "Party",
        "gender": "Women",
        "season": "All Season",
        "inventory": 61,
        "rating": 4.6,
        "discount": 20,
        "available_regions": [
            "Coimbatore",
            "Indore",
            "Jaipur",
            "Lucknow",
            "Nagpur",
            "Patna"
        ]
    },
    {
        "product_id": "P0061",
        "seller_id": "S012",
        "title": "Sangria Red Silk Saree",
        "brand": "Sangria",
        "category": "Saree",
        "price": 1599,
        "color": "Red",
        "material": "Silk",
        "occasion": "Wedding",
        "gender": "Women",
        "season": "All Season",
        "inventory": 116,
        "rating": 4.4,
        "discount": 15,
        "available_regions": [
            "Indore",
            "Nagpur",
            "Patna"
        ]
    },
    {
        "product_id": "P0062",
        "seller_id": "S006",
        "title": "Anouk Green Silk Saree",
        "brand": "Anouk",
        "category": "Saree",
        "price": 2999,
        "color": "Green",
        "material": "Silk",
        "occasion": "Wedding",
        "gender": "Women",
        "season": "All Season",
        "inventory": 97,
        "rating": 4.5,
        "discount": 20,
        "available_regions": [
            "Coimbatore",
            "Indore",
            "Jaipur",
            "Patna"
        ]
    },
    {
        "product_id": "P0063",
        "seller_id": "S013",
        "title": "Mitera Blue Georgette Saree",
        "brand": "Mitera",
        "category": "Saree",
        "price": 1599,
        "color": "Blue",
        "material": "Georgette",
        "occasion": "Wedding",
        "gender": "Women",
        "season": "Festive",
        "inventory": 110,
        "rating": 4.1,
        "discount": 15,
        "available_regions": [
            "Coimbatore",
            "Jaipur",
            "Patna"
        ]
    },
    {
        "product_id": "P0064",
        "seller_id": "S014",
        "title": "Mitera Green Chiffon Saree",
        "brand": "Mitera",
        "category": "Saree",
        "price": 2599,
        "color": "Green",
        "material": "Chiffon",
        "occasion": "Party",
        "gender": "Women",
        "season": "All Season",
        "inventory": 54,
        "rating": 4.6,
        "discount": 15,
        "available_regions": [
            "Coimbatore",
            "Indore",
            "Jaipur",
            "Lucknow",
            "Nagpur"
        ]
    },
    {
        "product_id": "P0065",
        "seller_id": "S005",
        "title": "Sangria Blue Georgette Saree",
        "brand": "Sangria",
        "category": "Saree",
        "price": 4799,
        "color": "Blue",
        "material": "Georgette",
        "occasion": "Party",
        "gender": "Women",
        "season": "Festive",
        "inventory": 93,
        "rating": 4.5,
        "discount": 20,
        "available_regions": [
            "Coimbatore",
            "Indore",
            "Jaipur",
            "Lucknow",
            "Nagpur",
            "Patna"
        ]
    },
    {
        "product_id": "P0066",
        "seller_id": "S011",
        "title": "Kalini Red Georgette Saree",
        "brand": "Kalini",
        "category": "Saree",
        "price": 1799,
        "color": "Red",
        "material": "Georgette",
        "occasion": "Party",
        "gender": "Women",
        "season": "All Season",
        "inventory": 109,
        "rating": 4.2,
        "discount": 10,
        "available_regions": [
            "Indore",
            "Jaipur",
            "Lucknow",
            "Nagpur",
            "Patna"
        ]
    },
    {
        "product_id": "P0067",
        "seller_id": "S001",
        "title": "Anouk Black Silk Saree",
        "brand": "Anouk",
        "category": "Saree",
        "price": 1599,
        "color": "Black",
        "material": "Silk",
        "occasion": "Wedding",
        "gender": "Women",
        "season": "Festive",
        "inventory": 153,
        "rating": 4.3,
        "discount": 20,
        "available_regions": [
            "Coimbatore",
            "Jaipur",
            "Lucknow",
            "Nagpur"
        ]
    },
    {
        "product_id": "P0068",
        "seller_id": "S003",
        "title": "Mitera Pink Georgette Saree",
        "brand": "Mitera",
        "category": "Saree",
        "price": 2999,
        "color": "Pink",
        "material": "Georgette",
        "occasion": "Party",
        "gender": "Women",
        "season": "All Season",
        "inventory": 39,
        "rating": 4.3,
        "discount": 15,
        "available_regions": [
            "Coimbatore",
            "Jaipur",
            "Lucknow",
            "Nagpur",
            "Patna"
        ]
    },
    {
        "product_id": "P0069",
        "seller_id": "S008",
        "title": "Sangria Red Cotton Saree",
        "brand": "Sangria",
        "category": "Saree",
        "price": 2599,
        "color": "Red",
        "material": "Cotton",
        "occasion": "Festive",
        "gender": "Women",
        "season": "All Season",
        "inventory": 168,
        "rating": 4.5,
        "discount": 25,
        "available_regions": [
            "Coimbatore",
            "Indore",
            "Jaipur",
            "Lucknow",
            "Nagpur",
            "Patna"
        ]
    },
    {
        "product_id": "P0070",
        "seller_id": "S010",
        "title": "Sangria Blue Silk Saree",
        "brand": "Sangria",
        "category": "Saree",
        "price": 2299,
        "color": "Blue",
        "material": "Silk",
        "occasion": "Wedding",
        "gender": "Women",
        "season": "All Season",
        "inventory": 43,
        "rating": 4.9,
        "discount": 20,
        "available_regions": [
            "Coimbatore",
            "Indore",
            "Jaipur",
            "Lucknow",
            "Nagpur",
            "Patna"
        ]
    },
    {
        "product_id": "P0071",
        "seller_id": "S012",
        "title": "Mitera Black Silk Saree",
        "brand": "Mitera",
        "category": "Saree",
        "price": 1199,
        "color": "Black",
        "material": "Silk",
        "occasion": "Party",
        "gender": "Women",
        "season": "All Season",
        "inventory": 46,
        "rating": 4.5,
        "discount": 15,
        "available_regions": [
            "Coimbatore",
            "Lucknow",
            "Nagpur",
            "Patna"
        ]
    },
    {
        "product_id": "P0072",
        "seller_id": "S005",
        "title": "Mitera Pink Cotton Saree",
        "brand": "Mitera",
        "category": "Saree",
        "price": 2499,
        "color": "Pink",
        "material": "Cotton",
        "occasion": "Festive",
        "gender": "Women",
        "season": "All Season",
        "inventory": 60,
        "rating": 4.6,
        "discount": 10,
        "available_regions": [
            "Coimbatore",
            "Indore",
            "Jaipur",
            "Lucknow",
            "Nagpur",
            "Patna"
        ]
    },
    {
        "product_id": "P0073",
        "seller_id": "S014",
        "title": "Kalini Green Cotton Saree",
        "brand": "Kalini",
        "category": "Saree",
        "price": 2499,
        "color": "Green",
        "material": "Cotton",
        "occasion": "Festive",
        "gender": "Women",
        "season": "Festive",
        "inventory": 65,
        "rating": 4.2,
        "discount": 20,
        "available_regions": [
            "Indore",
            "Jaipur",
            "Lucknow",
            "Nagpur",
            "Patna"
        ]
    },
    {
        "product_id": "P0074",
        "seller_id": "S011",
        "title": "Mitera Red Georgette Saree",
        "brand": "Mitera",
        "category": "Saree",
        "price": 2699,
        "color": "Red",
        "material": "Georgette",
        "occasion": "Party",
        "gender": "Women",
        "season": "All Season",
        "inventory": 43,
        "rating": 4.4,
        "discount": 0,
        "available_regions": [
            "Coimbatore",
            "Indore",
            "Jaipur",
            "Lucknow",
            "Nagpur",
            "Patna"
        ]
    },
    {
        "product_id": "P0075",
        "seller_id": "S007",
        "title": "Kalini Pink Silk Saree",
        "brand": "Kalini",
        "category": "Saree",
        "price": 1299,
        "color": "Pink",
        "material": "Silk",
        "occasion": "Wedding",
        "gender": "Women",
        "season": "All Season",
        "inventory": 51,
        "rating": 4.6,
        "discount": 20,
        "available_regions": [
            "Coimbatore",
            "Jaipur",
            "Lucknow",
            "Nagpur",
            "Patna"
        ]
    },
    {
        "product_id": "P0076",
        "seller_id": "S011",
        "title": "Louis Philippe White Cotton Shirt",
        "brand": "Louis Philippe",
        "category": "Shirt",
        "price": 1299,
        "color": "White",
        "material": "Cotton",
        "occasion": "Office",
        "gender": "Men",
        "season": "Summer",
        "inventory": 83,
        "rating": 4.4,
        "discount": 15,
        "available_regions": [
            "Coimbatore",
            "Indore",
            "Jaipur",
            "Lucknow",
            "Nagpur",
            "Patna"
        ]
    },
    {
        "product_id": "P0077",
        "seller_id": "S004",
        "title": "Louis Philippe Blue Linen Shirt",
        "brand": "Louis Philippe",
        "category": "Shirt",
        "price": 1199,
        "color": "Blue",
        "material": "Linen",
        "occasion": "Office",
        "gender": "Men",
        "season": "All Season",
        "inventory": 94,
        "rating": 4.6,
        "discount": 10,
        "available_regions": [
            "Coimbatore",
            "Indore",
            "Jaipur",
            "Lucknow"
        ]
    },
    {
        "product_id": "P0078",
        "seller_id": "S002",
        "title": "Roadster Blue Cotton Shirt",
        "brand": "Roadster",
        "category": "Shirt",
        "price": 999,
        "color": "Blue",
        "material": "Cotton",
        "occasion": "Office",
        "gender": "Men",
        "season": "All Season",
        "inventory": 84,
        "rating": 4.2,
        "discount": 25,
        "available_regions": [
            "Coimbatore",
            "Indore",
            "Jaipur",
            "Lucknow",
            "Nagpur",
            "Patna"
        ]
    },
    {
        "product_id": "P0079",
        "seller_id": "S007",
        "title": "Roadster Black Cotton Shirt",
        "brand": "Roadster",
        "category": "Shirt",
        "price": 1399,
        "color": "Black",
        "material": "Cotton",
        "occasion": "Casual",
        "gender": "Men",
        "season": "Summer",
        "inventory": 38,
        "rating": 4.3,
        "discount": 25,
        "available_regions": [
            "Coimbatore",
            "Indore",
            "Jaipur",
            "Lucknow",
            "Nagpur",
            "Patna"
        ]
    },
    {
        "product_id": "P0080",
        "seller_id": "S002",
        "title": "Highlander Blue Linen Shirt",
        "brand": "Highlander",
        "category": "Shirt",
        "price": 1399,
        "color": "Blue",
        "material": "Linen",
        "occasion": "Casual",
        "gender": "Men",
        "season": "All Season",
        "inventory": 88,
        "rating": 4.5,
        "discount": 15,
        "available_regions": [
            "Coimbatore",
            "Indore",
            "Jaipur",
            "Lucknow",
            "Nagpur",
            "Patna"
        ]
    },
    {
        "product_id": "P0081",
        "seller_id": "S006",
        "title": "Louis Philippe Grey Cotton Shirt",
        "brand": "Louis Philippe",
        "category": "Shirt",
        "price": 799,
        "color": "Grey",
        "material": "Cotton",
        "occasion": "Casual",
        "gender": "Men",
        "season": "All Season",
        "inventory": 111,
        "rating": 4.6,
        "discount": 15,
        "available_regions": [
            "Indore",
            "Jaipur",
            "Lucknow",
            "Patna"
        ]
    },
    {
        "product_id": "P0082",
        "seller_id": "S002",
        "title": "Louis Philippe Black Cotton Shirt",
        "brand": "Louis Philippe",
        "category": "Shirt",
        "price": 1099,
        "color": "Black",
        "material": "Cotton",
        "occasion": "Casual",
        "gender": "Men",
        "season": "All Season",
        "inventory": 48,
        "rating": 4.6,
        "discount": 25,
        "available_regions": [
            "Coimbatore",
            "Indore",
            "Patna"
        ]
    },
    {
        "product_id": "P0083",
        "seller_id": "S009",
        "title": "Roadster Olive Cotton Shirt",
        "brand": "Roadster",
        "category": "Shirt",
        "price": 1999,
        "color": "Olive",
        "material": "Cotton",
        "occasion": "Office",
        "gender": "Men",
        "season": "All Season",
        "inventory": 106,
        "rating": 4.0,
        "discount": 0,
        "available_regions": [
            "Indore",
            "Jaipur",
            "Lucknow",
            "Nagpur",
            "Patna"
        ]
    },
    {
        "product_id": "P0084",
        "seller_id": "S001",
        "title": "Roadster Black Linen Shirt",
        "brand": "Roadster",
        "category": "Shirt",
        "price": 1299,
        "color": "Black",
        "material": "Linen",
        "occasion": "Casual",
        "gender": "Men",
        "season": "All Season",
        "inventory": 71,
        "rating": 4.3,
        "discount": 15,
        "available_regions": [
            "Coimbatore",
            "Indore",
            "Jaipur",
            "Lucknow",
            "Patna"
        ]
    },
    {
        "product_id": "P0085",
        "seller_id": "S010",
        "title": "Louis Philippe Grey Linen Shirt",
        "brand": "Louis Philippe",
        "category": "Shirt",
        "price": 2799,
        "color": "Grey",
        "material": "Linen",
        "occasion": "Office",
        "gender": "Men",
        "season": "Summer",
        "inventory": 60,
        "rating": 4.4,
        "discount": 15,
        "available_regions": [
            "Coimbatore",
            "Indore",
            "Jaipur",
            "Lucknow",
            "Nagpur",
            "Patna"
        ]
    },
    {
        "product_id": "P0086",
        "seller_id": "S005",
        "title": "Highlander Black Linen Shirt",
        "brand": "Highlander",
        "category": "Shirt",
        "price": 899,
        "color": "Black",
        "material": "Linen",
        "occasion": "Office",
        "gender": "Men",
        "season": "All Season",
        "inventory": 94,
        "rating": 4.6,
        "discount": 20,
        "available_regions": [
            "Coimbatore",
            "Indore",
            "Jaipur",
            "Lucknow",
            "Nagpur",
            "Patna"
        ]
    },
    {
        "product_id": "P0087",
        "seller_id": "S003",
        "title": "Roadster Olive Linen Shirt",
        "brand": "Roadster",
        "category": "Shirt",
        "price": 799,
        "color": "Olive",
        "material": "Linen",
        "occasion": "Casual",
        "gender": "Men",
        "season": "All Season",
        "inventory": 104,
        "rating": 4.3,
        "discount": 25,
        "available_regions": [
            "Coimbatore",
            "Indore",
            "Jaipur",
            "Lucknow",
            "Nagpur",
            "Patna"
        ]
    },
    {
        "product_id": "P0088",
        "seller_id": "S013",
        "title": "Roadster White Linen Shirt",
        "brand": "Roadster",
        "category": "Shirt",
        "price": 1099,
        "color": "White",
        "material": "Linen",
        "occasion": "Casual",
        "gender": "Men",
        "season": "Summer",
        "inventory": 77,
        "rating": 4.5,
        "discount": 15,
        "available_regions": [
            "Coimbatore",
            "Indore",
            "Jaipur",
            "Lucknow",
            "Nagpur",
            "Patna"
        ]
    },
    {
        "product_id": "P0089",
        "seller_id": "S003",
        "title": "Allen Solly Blue Cotton Shirt",
        "brand": "Allen Solly",
        "category": "Shirt",
        "price": 1699,
        "color": "Blue",
        "material": "Cotton",
        "occasion": "Office",
        "gender": "Men",
        "season": "Summer",
        "inventory": 138,
        "rating": 4.7,
        "discount": 10,
        "available_regions": [
            "Coimbatore",
            "Lucknow",
            "Patna"
        ]
    },
    {
        "product_id": "P0090",
        "seller_id": "S006",
        "title": "Allen Solly Olive Cotton Shirt",
        "brand": "Allen Solly",
        "category": "Shirt",
        "price": 1099,
        "color": "Olive",
        "material": "Cotton",
        "occasion": "Office",
        "gender": "Men",
        "season": "All Season",
        "inventory": 73,
        "rating": 4.3,
        "discount": 20,
        "available_regions": [
            "Coimbatore",
            "Indore",
            "Jaipur",
            "Lucknow",
            "Patna"
        ]
    },
    {
        "product_id": "P0091",
        "seller_id": "S011",
        "title": "Highlander White Cotton Shirt",
        "brand": "Highlander",
        "category": "Shirt",
        "price": 999,
        "color": "White",
        "material": "Cotton",
        "occasion": "Casual",
        "gender": "Men",
        "season": "All Season",
        "inventory": 106,
        "rating": 4.6,
        "discount": 30,
        "available_regions": [
            "Indore",
            "Jaipur",
            "Lucknow"
        ]
    },
    {
        "product_id": "P0092",
        "seller_id": "S014",
        "title": "Highlander Blue Cotton Shirt",
        "brand": "Highlander",
        "category": "Shirt",
        "price": 1999,
        "color": "Blue",
        "material": "Cotton",
        "occasion": "Office",
        "gender": "Men",
        "season": "Summer",
        "inventory": 94,
        "rating": 4.3,
        "discount": 10,
        "available_regions": [
            "Coimbatore",
            "Indore",
            "Jaipur",
            "Nagpur",
            "Patna"
        ]
    },
    {
        "product_id": "P0093",
        "seller_id": "S009",
        "title": "Highlander Grey Cotton Shirt",
        "brand": "Highlander",
        "category": "Shirt",
        "price": 1099,
        "color": "Grey",
        "material": "Cotton",
        "occasion": "Office",
        "gender": "Men",
        "season": "All Season",
        "inventory": 97,
        "rating": 4.5,
        "discount": 15,
        "available_regions": [
            "Coimbatore",
            "Indore",
            "Jaipur",
            "Lucknow",
            "Nagpur",
            "Patna"
        ]
    },
    {
        "product_id": "P0094",
        "seller_id": "S009",
        "title": "Allen Solly Grey Cotton Shirt",
        "brand": "Allen Solly",
        "category": "Shirt",
        "price": 2099,
        "color": "Grey",
        "material": "Cotton",
        "occasion": "Office",
        "gender": "Men",
        "season": "Summer",
        "inventory": 53,
        "rating": 4.0,
        "discount": 10,
        "available_regions": [
            "Coimbatore",
            "Indore",
            "Jaipur",
            "Lucknow",
            "Nagpur",
            "Patna"
        ]
    },
    {
        "product_id": "P0095",
        "seller_id": "S006",
        "title": "Louis Philippe Black Linen Shirt",
        "brand": "Louis Philippe",
        "category": "Shirt",
        "price": 1299,
        "color": "Black",
        "material": "Linen",
        "occasion": "Casual",
        "gender": "Men",
        "season": "All Season",
        "inventory": 92,
        "rating": 4.5,
        "discount": 15,
        "available_regions": [
            "Coimbatore",
            "Indore",
            "Jaipur",
            "Lucknow",
            "Nagpur"
        ]
    },
    {
        "product_id": "P0096",
        "seller_id": "S006",
        "title": "Louis Philippe White Linen Shirt",
        "brand": "Louis Philippe",
        "category": "Shirt",
        "price": 1799,
        "color": "White",
        "material": "Linen",
        "occasion": "Casual",
        "gender": "Men",
        "season": "Summer",
        "inventory": 60,
        "rating": 4.3,
        "discount": 15,
        "available_regions": [
            "Coimbatore",
            "Indore",
            "Jaipur",
            "Patna"
        ]
    },
    {
        "product_id": "P0097",
        "seller_id": "S002",
        "title": "Louis Philippe Blue Cotton Shirt",
        "brand": "Louis Philippe",
        "category": "Shirt",
        "price": 1399,
        "color": "Blue",
        "material": "Cotton",
        "occasion": "Office",
        "gender": "Men",
        "season": "Summer",
        "inventory": 70,
        "rating": 4.2,
        "discount": 25,
        "available_regions": [
            "Jaipur",
            "Lucknow",
            "Nagpur",
            "Patna"
        ]
    },
    {
        "product_id": "P0098",
        "seller_id": "S009",
        "title": "Highlander Black Cotton Shirt",
        "brand": "Highlander",
        "category": "Shirt",
        "price": 1099,
        "color": "Black",
        "material": "Cotton",
        "occasion": "Office",
        "gender": "Men",
        "season": "Summer",
        "inventory": 55,
        "rating": 4.2,
        "discount": 10,
        "available_regions": [
            "Coimbatore",
            "Jaipur",
            "Lucknow",
            "Nagpur"
        ]
    },
    {
        "product_id": "P0099",
        "seller_id": "S014",
        "title": "Allen Solly Grey Linen Shirt",
        "brand": "Allen Solly",
        "category": "Shirt",
        "price": 2199,
        "color": "Grey",
        "material": "Linen",
        "occasion": "Casual",
        "gender": "Men",
        "season": "Summer",
        "inventory": 133,
        "rating": 4.6,
        "discount": 25,
        "available_regions": [
            "Coimbatore",
            "Indore",
            "Jaipur",
            "Lucknow",
            "Patna"
        ]
    },
    {
        "product_id": "P0100",
        "seller_id": "S004",
        "title": "Roadster White Cotton Shirt",
        "brand": "Roadster",
        "category": "Shirt",
        "price": 2599,
        "color": "White",
        "material": "Cotton",
        "occasion": "Office",
        "gender": "Men",
        "season": "All Season",
        "inventory": 117,
        "rating": 4.2,
        "discount": 30,
        "available_regions": [
            "Coimbatore",
            "Indore",
            "Jaipur",
            "Nagpur",
            "Patna"
        ]
    },
    {
        "product_id": "P0101",
        "seller_id": "S007",
        "title": "Louis Philippe Olive Linen Shirt",
        "brand": "Louis Philippe",
        "category": "Shirt",
        "price": 799,
        "color": "Olive",
        "material": "Linen",
        "occasion": "Casual",
        "gender": "Men",
        "season": "Summer",
        "inventory": 58,
        "rating": 4.3,
        "discount": 15,
        "available_regions": [
            "Coimbatore",
            "Indore",
            "Jaipur",
            "Lucknow",
            "Nagpur",
            "Patna"
        ]
    },
    {
        "product_id": "P0102",
        "seller_id": "S003",
        "title": "Allen Solly White Cotton Shirt",
        "brand": "Allen Solly",
        "category": "Shirt",
        "price": 1799,
        "color": "White",
        "material": "Cotton",
        "occasion": "Office",
        "gender": "Men",
        "season": "Summer",
        "inventory": 90,
        "rating": 4.2,
        "discount": 10,
        "available_regions": [
            "Coimbatore",
            "Indore",
            "Lucknow",
            "Nagpur"
        ]
    },
    {
        "product_id": "P0103",
        "seller_id": "S012",
        "title": "Roadster Blue Linen Shirt",
        "brand": "Roadster",
        "category": "Shirt",
        "price": 999,
        "color": "Blue",
        "material": "Linen",
        "occasion": "Casual",
        "gender": "Men",
        "season": "All Season",
        "inventory": 73,
        "rating": 4.2,
        "discount": 15,
        "available_regions": [
            "Coimbatore",
            "Indore",
            "Jaipur",
            "Lucknow",
            "Patna"
        ]
    },
    {
        "product_id": "P0104",
        "seller_id": "S010",
        "title": "Louis Philippe Olive Cotton Shirt",
        "brand": "Louis Philippe",
        "category": "Shirt",
        "price": 1099,
        "color": "Olive",
        "material": "Cotton",
        "occasion": "Casual",
        "gender": "Men",
        "season": "All Season",
        "inventory": 131,
        "rating": 4.5,
        "discount": 10,
        "available_regions": [
            "Coimbatore",
            "Jaipur",
            "Lucknow",
            "Patna"
        ]
    },
    {
        "product_id": "P0105",
        "seller_id": "S006",
        "title": "Highlander Olive Cotton Shirt",
        "brand": "Highlander",
        "category": "Shirt",
        "price": 1099,
        "color": "Olive",
        "material": "Cotton",
        "occasion": "Office",
        "gender": "Men",
        "season": "Summer",
        "inventory": 111,
        "rating": 4.4,
        "discount": 15,
        "available_regions": [
            "Indore",
            "Lucknow",
            "Nagpur",
            "Patna"
        ]
    },
    {
        "product_id": "P0106",
        "seller_id": "S001",
        "title": "HRX White Mesh Sneakers",
        "brand": "HRX",
        "category": "Sneakers",
        "price": 3699,
        "color": "White",
        "material": "Mesh",
        "occasion": "Casual",
        "gender": "Unisex",
        "season": "All Season",
        "inventory": 88,
        "rating": 4.1,
        "discount": 25,
        "available_regions": [
            "Coimbatore",
            "Indore",
            "Nagpur",
            "Patna"
        ]
    },
    {
        "product_id": "P0107",
        "seller_id": "S015",
        "title": "Adidas Black Synthetic Sneakers",
        "brand": "Adidas",
        "category": "Sneakers",
        "price": 2099,
        "color": "Black",
        "material": "Synthetic",
        "occasion": "Sports",
        "gender": "Unisex",
        "season": "All Season",
        "inventory": 78,
        "rating": 4.5,
        "discount": 25,
        "available_regions": [
            "Coimbatore",
            "Indore",
            "Jaipur",
            "Lucknow",
            "Nagpur"
        ]
    },
    {
        "product_id": "P0108",
        "seller_id": "S009",
        "title": "Puma White Mesh Sneakers",
        "brand": "Puma",
        "category": "Sneakers",
        "price": 4799,
        "color": "White",
        "material": "Mesh",
        "occasion": "Sports",
        "gender": "Unisex",
        "season": "All Season",
        "inventory": 112,
        "rating": 4.2,
        "discount": 20,
        "available_regions": [
            "Coimbatore",
            "Indore",
            "Jaipur",
            "Lucknow",
            "Nagpur"
        ]
    },
    {
        "product_id": "P0109",
        "seller_id": "S015",
        "title": "Adidas Black Canvas Sneakers",
        "brand": "Adidas",
        "category": "Sneakers",
        "price": 2699,
        "color": "Black",
        "material": "Canvas",
        "occasion": "Casual",
        "gender": "Unisex",
        "season": "All Season",
        "inventory": 44,
        "rating": 4.3,
        "discount": 10,
        "available_regions": [
            "Coimbatore",
            "Indore",
            "Lucknow",
            "Nagpur"
        ]
    },
    {
        "product_id": "P0110",
        "seller_id": "S009",
        "title": "Adidas Black Mesh Sneakers",
        "brand": "Adidas",
        "category": "Sneakers",
        "price": 4699,
        "color": "Black",
        "material": "Mesh",
        "occasion": "Sports",
        "gender": "Unisex",
        "season": "All Season",
        "inventory": 89,
        "rating": 4.6,
        "discount": 10,
        "available_regions": [
            "Coimbatore",
            "Indore",
            "Jaipur",
            "Lucknow",
            "Nagpur",
            "Patna"
        ]
    },
    {
        "product_id": "P0111",
        "seller_id": "S010",
        "title": "HRX Black Synthetic Sneakers",
        "brand": "HRX",
        "category": "Sneakers",
        "price": 1599,
        "color": "Black",
        "material": "Synthetic",
        "occasion": "Sports",
        "gender": "Unisex",
        "season": "All Season",
        "inventory": 45,
        "rating": 4.5,
        "discount": 20,
        "available_regions": [
            "Coimbatore",
            "Lucknow",
            "Patna"
        ]
    },
    {
        "product_id": "P0112",
        "seller_id": "S007",
        "title": "Nike White Mesh Sneakers",
        "brand": "Nike",
        "category": "Sneakers",
        "price": 2399,
        "color": "White",
        "material": "Mesh",
        "occasion": "Sports",
        "gender": "Unisex",
        "season": "All Season",
        "inventory": 101,
        "rating": 4.3,
        "discount": 30,
        "available_regions": [
            "Coimbatore",
            "Indore",
            "Jaipur",
            "Lucknow",
            "Nagpur",
            "Patna"
        ]
    },
    {
        "product_id": "P0113",
        "seller_id": "S001",
        "title": "Nike Black Mesh Sneakers",
        "brand": "Nike",
        "category": "Sneakers",
        "price": 3799,
        "color": "Black",
        "material": "Mesh",
        "occasion": "Sports",
        "gender": "Unisex",
        "season": "All Season",
        "inventory": 107,
        "rating": 4.4,
        "discount": 20,
        "available_regions": [
            "Coimbatore",
            "Indore",
            "Jaipur",
            "Lucknow",
            "Nagpur",
            "Patna"
        ]
    },
    {
        "product_id": "P0114",
        "seller_id": "S002",
        "title": "Puma Black Synthetic Sneakers",
        "brand": "Puma",
        "category": "Sneakers",
        "price": 1699,
        "color": "Black",
        "material": "Synthetic",
        "occasion": "Casual",
        "gender": "Unisex",
        "season": "All Season",
        "inventory": 112,
        "rating": 4.5,
        "discount": 20,
        "available_regions": [
            "Jaipur",
            "Lucknow",
            "Patna"
        ]
    },
    {
        "product_id": "P0115",
        "seller_id": "S009",
        "title": "Puma Grey Synthetic Sneakers",
        "brand": "Puma",
        "category": "Sneakers",
        "price": 1999,
        "color": "Grey",
        "material": "Synthetic",
        "occasion": "Sports",
        "gender": "Unisex",
        "season": "All Season",
        "inventory": 77,
        "rating": 4.5,
        "discount": 30,
        "available_regions": [
            "Coimbatore",
            "Lucknow",
            "Nagpur",
            "Patna"
        ]
    },
    {
        "product_id": "P0116",
        "seller_id": "S007",
        "title": "HRX Blue Mesh Sneakers",
        "brand": "HRX",
        "category": "Sneakers",
        "price": 2499,
        "color": "Blue",
        "material": "Mesh",
        "occasion": "Sports",
        "gender": "Unisex",
        "season": "All Season",
        "inventory": 75,
        "rating": 4.5,
        "discount": 20,
        "available_regions": [
            "Coimbatore",
            "Indore",
            "Jaipur",
            "Patna"
        ]
    },
    {
        "product_id": "P0117",
        "seller_id": "S004",
        "title": "HRX Black Mesh Sneakers",
        "brand": "HRX",
        "category": "Sneakers",
        "price": 2099,
        "color": "Black",
        "material": "Mesh",
        "occasion": "Casual",
        "gender": "Unisex",
        "season": "All Season",
        "inventory": 75,
        "rating": 4.5,
        "discount": 15,
        "available_regions": [
            "Coimbatore",
            "Jaipur",
            "Lucknow",
            "Nagpur",
            "Patna"
        ]
    },
    {
        "product_id": "P0118",
        "seller_id": "S005",
        "title": "Puma Black Mesh Sneakers",
        "brand": "Puma",
        "category": "Sneakers",
        "price": 5099,
        "color": "Black",
        "material": "Mesh",
        "occasion": "Sports",
        "gender": "Unisex",
        "season": "All Season",
        "inventory": 138,
        "rating": 4.4,
        "discount": 30,
        "available_regions": [
            "Coimbatore",
            "Jaipur",
            "Patna"
        ]
    },
    {
        "product_id": "P0119",
        "seller_id": "S012",
        "title": "Adidas White Mesh Sneakers",
        "brand": "Adidas",
        "category": "Sneakers",
        "price": 1799,
        "color": "White",
        "material": "Mesh",
        "occasion": "Sports",
        "gender": "Unisex",
        "season": "All Season",
        "inventory": 76,
        "rating": 4.9,
        "discount": 20,
        "available_regions": [
            "Coimbatore",
            "Indore",
            "Jaipur",
            "Lucknow",
            "Nagpur",
            "Patna"
        ]
    },
    {
        "product_id": "P0120",
        "seller_id": "S013",
        "title": "Puma White Synthetic Sneakers",
        "brand": "Puma",
        "category": "Sneakers",
        "price": 4099,
        "color": "White",
        "material": "Synthetic",
        "occasion": "Sports",
        "gender": "Unisex",
        "season": "All Season",
        "inventory": 115,
        "rating": 4.3,
        "discount": 15,
        "available_regions": [
            "Coimbatore",
            "Indore",
            "Jaipur",
            "Lucknow"
        ]
    },
    {
        "product_id": "P0121",
        "seller_id": "S013",
        "title": "Nike White Synthetic Sneakers",
        "brand": "Nike",
        "category": "Sneakers",
        "price": 1499,
        "color": "White",
        "material": "Synthetic",
        "occasion": "Casual",
        "gender": "Unisex",
        "season": "All Season",
        "inventory": 102,
        "rating": 4.6,
        "discount": 10,
        "available_regions": [
            "Jaipur",
            "Lucknow",
            "Nagpur",
            "Patna"
        ]
    },
    {
        "product_id": "P0122",
        "seller_id": "S001",
        "title": "Nike Black Synthetic Sneakers",
        "brand": "Nike",
        "category": "Sneakers",
        "price": 1499,
        "color": "Black",
        "material": "Synthetic",
        "occasion": "Casual",
        "gender": "Unisex",
        "season": "All Season",
        "inventory": 76,
        "rating": 4.4,
        "discount": 20,
        "available_regions": [
            "Coimbatore",
            "Indore",
            "Jaipur",
            "Lucknow",
            "Nagpur"
        ]
    },
    {
        "product_id": "P0123",
        "seller_id": "S006",
        "title": "Nike Black Canvas Sneakers",
        "brand": "Nike",
        "category": "Sneakers",
        "price": 5199,
        "color": "Black",
        "material": "Canvas",
        "occasion": "Casual",
        "gender": "Unisex",
        "season": "All Season",
        "inventory": 61,
        "rating": 4.4,
        "discount": 20,
        "available_regions": [
            "Coimbatore",
            "Jaipur",
            "Lucknow",
            "Nagpur",
            "Patna"
        ]
    },
    {
        "product_id": "P0124",
        "seller_id": "S012",
        "title": "HRX White Canvas Sneakers",
        "brand": "HRX",
        "category": "Sneakers",
        "price": 1599,
        "color": "White",
        "material": "Canvas",
        "occasion": "Casual",
        "gender": "Unisex",
        "season": "All Season",
        "inventory": 79,
        "rating": 4.2,
        "discount": 10,
        "available_regions": [
            "Indore",
            "Jaipur",
            "Lucknow",
            "Patna"
        ]
    },
    {
        "product_id": "P0125",
        "seller_id": "S012",
        "title": "Puma Grey Canvas Sneakers",
        "brand": "Puma",
        "category": "Sneakers",
        "price": 3899,
        "color": "Grey",
        "material": "Canvas",
        "occasion": "Casual",
        "gender": "Unisex",
        "season": "All Season",
        "inventory": 94,
        "rating": 4.6,
        "discount": 15,
        "available_regions": [
            "Indore",
            "Lucknow",
            "Patna"
        ]
    },
    {
        "product_id": "P0126",
        "seller_id": "S003",
        "title": "Nike Blue Synthetic Sneakers",
        "brand": "Nike",
        "category": "Sneakers",
        "price": 3499,
        "color": "Blue",
        "material": "Synthetic",
        "occasion": "Casual",
        "gender": "Unisex",
        "season": "All Season",
        "inventory": 89,
        "rating": 4.5,
        "discount": 15,
        "available_regions": [
            "Jaipur",
            "Lucknow",
            "Nagpur",
            "Patna"
        ]
    },
    {
        "product_id": "P0127",
        "seller_id": "S006",
        "title": "HRX White Synthetic Sneakers",
        "brand": "HRX",
        "category": "Sneakers",
        "price": 2599,
        "color": "White",
        "material": "Synthetic",
        "occasion": "Sports",
        "gender": "Unisex",
        "season": "All Season",
        "inventory": 96,
        "rating": 4.1,
        "discount": 20,
        "available_regions": [
            "Coimbatore",
            "Indore",
            "Jaipur",
            "Nagpur",
            "Patna"
        ]
    },
    {
        "product_id": "P0128",
        "seller_id": "S006",
        "title": "HRX Grey Mesh Sneakers",
        "brand": "HRX",
        "category": "Sneakers",
        "price": 1699,
        "color": "Grey",
        "material": "Mesh",
        "occasion": "Sports",
        "gender": "Unisex",
        "season": "All Season",
        "inventory": 49,
        "rating": 4.3,
        "discount": 20,
        "available_regions": [
            "Coimbatore",
            "Jaipur",
            "Patna"
        ]
    },
    {
        "product_id": "P0129",
        "seller_id": "S007",
        "title": "Adidas White Synthetic Sneakers",
        "brand": "Adidas",
        "category": "Sneakers",
        "price": 3399,
        "color": "White",
        "material": "Synthetic",
        "occasion": "Sports",
        "gender": "Unisex",
        "season": "All Season",
        "inventory": 93,
        "rating": 4.5,
        "discount": 15,
        "available_regions": [
            "Coimbatore",
            "Lucknow",
            "Nagpur",
            "Patna"
        ]
    },
    {
        "product_id": "P0130",
        "seller_id": "S011",
        "title": "HRX Black Canvas Sneakers",
        "brand": "HRX",
        "category": "Sneakers",
        "price": 2399,
        "color": "Black",
        "material": "Canvas",
        "occasion": "Casual",
        "gender": "Unisex",
        "season": "All Season",
        "inventory": 75,
        "rating": 4.4,
        "discount": 40,
        "available_regions": [
            "Coimbatore",
            "Indore",
            "Jaipur",
            "Lucknow",
            "Nagpur",
            "Patna"
        ]
    },
    {
        "product_id": "P0131",
        "seller_id": "S002",
        "title": "Nike White Canvas Sneakers",
        "brand": "Nike",
        "category": "Sneakers",
        "price": 3499,
        "color": "White",
        "material": "Canvas",
        "occasion": "Casual",
        "gender": "Unisex",
        "season": "All Season",
        "inventory": 116,
        "rating": 4.9,
        "discount": 10,
        "available_regions": [
            "Indore",
            "Jaipur",
            "Nagpur",
            "Patna"
        ]
    },
    {
        "product_id": "P0132",
        "seller_id": "S007",
        "title": "Puma Grey Mesh Sneakers",
        "brand": "Puma",
        "category": "Sneakers",
        "price": 5199,
        "color": "Grey",
        "material": "Mesh",
        "occasion": "Casual",
        "gender": "Unisex",
        "season": "All Season",
        "inventory": 50,
        "rating": 4.4,
        "discount": 20,
        "available_regions": [
            "Coimbatore",
            "Indore",
            "Jaipur",
            "Lucknow",
            "Nagpur",
            "Patna"
        ]
    },
    {
        "product_id": "P0133",
        "seller_id": "S013",
        "title": "Nike Grey Synthetic Sneakers",
        "brand": "Nike",
        "category": "Sneakers",
        "price": 1999,
        "color": "Grey",
        "material": "Synthetic",
        "occasion": "Sports",
        "gender": "Unisex",
        "season": "All Season",
        "inventory": 92,
        "rating": 4.2,
        "discount": 15,
        "available_regions": [
            "Coimbatore",
            "Indore",
            "Jaipur",
            "Lucknow",
            "Nagpur",
            "Patna"
        ]
    },
    {
        "product_id": "P0134",
        "seller_id": "S011",
        "title": "Adidas White Canvas Sneakers",
        "brand": "Adidas",
        "category": "Sneakers",
        "price": 2099,
        "color": "White",
        "material": "Canvas",
        "occasion": "Casual",
        "gender": "Unisex",
        "season": "All Season",
        "inventory": 56,
        "rating": 4.5,
        "discount": 20,
        "available_regions": [
            "Indore",
            "Nagpur",
            "Patna"
        ]
    },
    {
        "product_id": "P0135",
        "seller_id": "S012",
        "title": "HRX Grey Synthetic Sneakers",
        "brand": "HRX",
        "category": "Sneakers",
        "price": 2399,
        "color": "Grey",
        "material": "Synthetic",
        "occasion": "Sports",
        "gender": "Unisex",
        "season": "All Season",
        "inventory": 108,
        "rating": 4.5,
        "discount": 10,
        "available_regions": [
            "Coimbatore",
            "Indore",
            "Jaipur",
            "Lucknow",
            "Nagpur",
            "Patna"
        ]
    },
    {
        "product_id": "P0136",
        "seller_id": "S013",
        "title": "Wrangler Blue Denim Jeans",
        "brand": "Wrangler",
        "category": "Jeans",
        "price": 999,
        "color": "Blue",
        "material": "Denim",
        "occasion": "Casual",
        "gender": "Unisex",
        "season": "All Season",
        "inventory": 115,
        "rating": 4.6,
        "discount": 15,
        "available_regions": [
            "Jaipur",
            "Nagpur",
            "Patna"
        ]
    },
    {
        "product_id": "P0137",
        "seller_id": "S011",
        "title": "Levis Grey Denim Jeans",
        "brand": "Levis",
        "category": "Jeans",
        "price": 1399,
        "color": "Grey",
        "material": "Denim",
        "occasion": "Casual",
        "gender": "Unisex",
        "season": "All Season",
        "inventory": 116,
        "rating": 4.1,
        "discount": 10,
        "available_regions": [
            "Coimbatore",
            "Indore",
            "Lucknow",
            "Nagpur",
            "Patna"
        ]
    },
    {
        "product_id": "P0138",
        "seller_id": "S002",
        "title": "Levis Black Denim Jeans",
        "brand": "Levis",
        "category": "Jeans",
        "price": 2199,
        "color": "Black",
        "material": "Denim",
        "occasion": "Casual",
        "gender": "Unisex",
        "season": "All Season",
        "inventory": 108,
        "rating": 4.4,
        "discount": 10,
        "available_regions": [
            "Coimbatore",
            "Lucknow",
            "Nagpur",
            "Patna"
        ]
    },
    {
        "product_id": "P0139",
        "seller_id": "S002",
        "title": "Roadster Black Denim Jeans",
        "brand": "Roadster",
        "category": "Jeans",
        "price": 1299,
        "color": "Black",
        "material": "Denim",
        "occasion": "Casual",
        "gender": "Unisex",
        "season": "All Season",
        "inventory": 118,
        "rating": 4.6,
        "discount": 10,
        "available_regions": [
            "Coimbatore",
            "Indore",
            "Jaipur",
            "Lucknow",
            "Patna"
        ]
    },
    {
        "product_id": "P0140",
        "seller_id": "S004",
        "title": "Levis Blue Denim Jeans",
        "brand": "Levis",
        "category": "Jeans",
        "price": 1999,
        "color": "Blue",
        "material": "Denim",
        "occasion": "Casual",
        "gender": "Unisex",
        "season": "All Season",
        "inventory": 94,
        "rating": 4.6,
        "discount": 20,
        "available_regions": [
            "Coimbatore",
            "Jaipur",
            "Lucknow",
            "Nagpur"
        ]
    },
    {
        "product_id": "P0141",
        "seller_id": "S005",
        "title": "Roadster Blue Denim Jeans",
        "brand": "Roadster",
        "category": "Jeans",
        "price": 1999,
        "color": "Blue",
        "material": "Denim",
        "occasion": "Casual",
        "gender": "Unisex",
        "season": "All Season",
        "inventory": 80,
        "rating": 4.7,
        "discount": 20,
        "available_regions": [
            "Coimbatore",
            "Indore",
            "Lucknow",
            "Nagpur",
            "Patna"
        ]
    },
    {
        "product_id": "P0142",
        "seller_id": "S010",
        "title": "Pepe Jeans Grey Denim Jeans",
        "brand": "Pepe Jeans",
        "category": "Jeans",
        "price": 1599,
        "color": "Grey",
        "material": "Denim",
        "occasion": "Casual",
        "gender": "Unisex",
        "season": "All Season",
        "inventory": 65,
        "rating": 4.4,
        "discount": 15,
        "available_regions": [
            "Coimbatore",
            "Lucknow",
            "Nagpur"
        ]
    },
    {
        "product_id": "P0143",
        "seller_id": "S010",
        "title": "Pepe Jeans Blue Denim Jeans",
        "brand": "Pepe Jeans",
        "category": "Jeans",
        "price": 1899,
        "color": "Blue",
        "material": "Denim",
        "occasion": "Casual",
        "gender": "Unisex",
        "season": "All Season",
        "inventory": 65,
        "rating": 4.7,
        "discount": 20,
        "available_regions": [
            "Coimbatore",
            "Jaipur",
            "Lucknow"
        ]
    },
    {
        "product_id": "P0144",
        "seller_id": "S014",
        "title": "Wrangler Grey Denim Jeans",
        "brand": "Wrangler",
        "category": "Jeans",
        "price": 1499,
        "color": "Grey",
        "material": "Denim",
        "occasion": "Casual",
        "gender": "Unisex",
        "season": "All Season",
        "inventory": 72,
        "rating": 4.4,
        "discount": 20,
        "available_regions": [
            "Coimbatore",
            "Indore",
            "Jaipur",
            "Nagpur"
        ]
    },
    {
        "product_id": "P0145",
        "seller_id": "S011",
        "title": "Roadster Grey Denim Jeans",
        "brand": "Roadster",
        "category": "Jeans",
        "price": 1599,
        "color": "Grey",
        "material": "Denim",
        "occasion": "Casual",
        "gender": "Unisex",
        "season": "All Season",
        "inventory": 117,
        "rating": 4.7,
        "discount": 25,
        "available_regions": [
            "Coimbatore",
            "Indore",
            "Lucknow",
            "Nagpur",
            "Patna"
        ]
    },
    {
        "product_id": "P0146",
        "seller_id": "S009",
        "title": "Wrangler Black Denim Jeans",
        "brand": "Wrangler",
        "category": "Jeans",
        "price": 2099,
        "color": "Black",
        "material": "Denim",
        "occasion": "Casual",
        "gender": "Unisex",
        "season": "All Season",
        "inventory": 119,
        "rating": 4.2,
        "discount": 10,
        "available_regions": [
            "Indore",
            "Lucknow",
            "Nagpur",
            "Patna"
        ]
    },
    {
        "product_id": "P0147",
        "seller_id": "S004",
        "title": "Pepe Jeans Black Denim Jeans",
        "brand": "Pepe Jeans",
        "category": "Jeans",
        "price": 1299,
        "color": "Black",
        "material": "Denim",
        "occasion": "Casual",
        "gender": "Unisex",
        "season": "All Season",
        "inventory": 97,
        "rating": 4.5,
        "discount": 10,
        "available_regions": [
            "Lucknow",
            "Nagpur",
            "Patna"
        ]
    }
]